cfx/Endpoint.py
cfx/There.py
cfx/__init__.py
cfx/cfx.py
cfx/Production/__init__.py
cfx/Production/TestAndInspection/UnitsInspected.py
cfx/Production/TestAndInspection/UnitsTested.py
cfx/Production/TestAndInspection/__init__.py
cfx/Structures/ActorType.py
cfx/Structures/ComponentDesignator.py
cfx/Structures/Defect.py
cfx/Structures/Image.py
cfx/Structures/InspectedUnit.py
cfx/Structures/Inspection.py
cfx/Structures/InspectionMethod.py
cfx/Structures/Measurement.py
cfx/Structures/Operator.py
cfx/Structures/Region.py
cfx/Structures/SamplingInformation.py
cfx/Structures/SamplingMethod.py
cfx/Structures/Segment.py
cfx/Structures/Symptom.py
cfx/Structures/TestResult.py
cfx/Structures/UnitPosition.py
cfx/Structures/__init__.py
cfx/Structures/base.py
cfx/utils/__init__.py
cfx/utils/common.py
cfx/utils/factory.py
python_ipc_cfx-0.0.2.dist-info/METADATA
python_ipc_cfx-0.0.2.dist-info/WHEEL
python_ipc_cfx-0.0.2.dist-info/top_level.txt
python_ipc_cfx-0.0.2.dist-info/RECORD
