Metadata-Version: 2.1
Name: python-ipc-cfx
Version: 0.0.2
Summary: Python implementation of the IPC-CFX standard
Home-page: https://github.com/iotile/python-ipc-cfx
Author: Arch
Author-email: info@archsys.io
License: proprietary
Keywords: iotile,arch,industrial
Platform: UNKNOWN
Classifier: Programming Language :: Python
Classifier: Development Status :: 5 - Production/Stable
Classifier: Operating System :: OS Independent
Classifier: Programming Language :: Python :: 3
Classifier: Programming Language :: Python :: 3.5
Classifier: Programming Language :: Python :: 3.6
Classifier: Programming Language :: Python :: 3.7
Classifier: Topic :: Software Development :: Libraries :: Python Modules
Requires-Python: >=3.5, <4
Requires-Dist: python-dateutil (>=2.8.0)
Requires-Dist: pytz (>=2019.2)
Requires-Dist: stringcase (>=1.2.0)
